microprediction/__init__.py
microprediction/conventions.py
microprediction/crawler.py
microprediction/defaultcrawler.py
microprediction/fitcrawler.py
microprediction/install.py
microprediction/looping.py
microprediction/old_conventions.py
microprediction/onlinecrawler.py
microprediction/polling.py
microprediction/pollingutil.py
microprediction/reader.py
microprediction/reportingcrawler.py
microprediction/samplers.py
microprediction/sequentialcrawler.py
microprediction/set_config.py
microprediction/simplecrawler.py
microprediction/slack.py
microprediction/statefulcrawler.py
microprediction/streamskater.py
microprediction/supporter.py
microprediction/whereami.py
microprediction/writer.py
microprediction/bespoke/__init__.py
microprediction/bespoke/meme_stock.py
microprediction/bespoke/crypto/__init__.py
microprediction/bespoke/crypto/cryptoconventions.py
microprediction/bespoke/golf/__init__.py
microprediction/bespoke/golf/golfconventions.py
microprediction/bespoke/meme_stocks/meme_stock.py
microprediction/inclusion/__init__.py
microprediction/inclusion/scipyinclusion.py
microprediction/inclusion/timemachinesinclusion.py
microprediction/inclusion/tsainclusion.py
microprediction/live/__init__.py
microprediction/live/bart_delays.py
microprediction/live/covid_news.py
microprediction/live/crypto.py
microprediction/live/faang.py
microprediction/live/grains.py
microprediction/live/iex.py
microprediction/live/iexcredentials.py
microprediction/live/nyc_bikes.py
microprediction/live/nyc_traffic.py
microprediction/live/pga.py
microprediction/live/rdpstickers.py
microprediction/live/seattle_wind.py
microprediction/live/tradingday.py
microprediction/live/water_height.py
microprediction/live/weightedmid.py
microprediction/live/xrayportfolios.py
microprediction/live/xrayprices.py
microprediction/live/xraytickers.py
microprediction/live/xraytickersdiscarded.py
microprediction/univariate/__init__.py
microprediction/univariate/arrivals.py
microprediction/univariate/cdfvalues.py
microprediction-1.2.0.dist-info/METADATA
microprediction-1.2.0.dist-info/WHEEL
microprediction-1.2.0.dist-info/entry_points.txt
microprediction-1.2.0.dist-info/top_level.txt
microprediction-1.2.0.dist-info/RECORD
