Metadata-Version: 2.1
Name: microprediction
Version: 1.2.0
Summary: Client for www.microprediction.org turnkey community prediction
Home-page: https://github.com/microprediction/microprediction
Author: microprediction
Author-email: info@microprediction.org
License: MIT
Platform: UNKNOWN
Classifier: License :: OSI Approved :: MIT License
Classifier: Programming Language :: Python :: 3
Classifier: Programming Language :: Python :: 3.7
Classifier: Programming Language :: Python :: 3.8
Requires-Dist: numpy (>=1.23.5)
Requires-Dist: pandas
Requires-Dist: contexttimer
Requires-Dist: requests
Requires-Dist: getjson (>=2.0.0)
Requires-Dist: microconventions (>=1.0.0)
Requires-Dist: pytz (>=2021.3)
Requires-Dist: pycoingecko
Requires-Dist: tdigest
Requires-Dist: genson
Requires-Dist: hyperopt
Requires-Dist: scikit-learn
Requires-Dist: statsmodels
Requires-Dist: copulas
